<?xml version="1.0" encoding="UTF-8"?>
<objects serializationModel="Studio.02.01.00">
	<object class="AudioFile" id="{65816bf9-35d6-4b74-87cb-e26b0c02e8ba}">
		<property name="assetPath">
			<value>靠右边（语速修复）.wav</value>
		</property>
		<property name="frequencyInKHz">
			<value>44.0999985</value>
		</property>
		<property name="channelCount">
			<value>2</value>
		</property>
		<property name="length">
			<value>0.6439455782312925</value>
		</property>
		<relationship name="masterAssetFolder">
			<destination>{6823c597-5285-4eea-92e9-487338792da0}</destination>
		</relationship>
	</object>
</objects>
