<?xml version="1.0" encoding="UTF-8"?>
<objects serializationModel="Studio.02.01.00">
	<object class="AudioFile" id="{ad3dd340-cba8-4c0e-a4b6-05326f6b335d}">
		<property name="assetPath">
			<value>speed_warning_4.wav</value>
		</property>
		<property name="frequencyInKHz">
			<value>48</value>
		</property>
		<property name="channelCount">
			<value>1</value>
		</property>
		<property name="length">
			<value>2.7149999999999999</value>
		</property>
		<relationship name="masterAssetFolder">
			<destination>{6823c597-5285-4eea-92e9-487338792da0}</destination>
		</relationship>
	</object>
</objects>
